setup.py
appdotnet/__init__.py
appdotnet/api.py
appdotnet/endpoints.py
appdotnet/exceptions.py
appdotnet/util.py
appdotnet.egg-info/PKG-INFO
appdotnet.egg-info/SOURCES.txt
appdotnet.egg-info/dependency_links.txt
appdotnet.egg-info/requires.txt
appdotnet.egg-info/top_level.txt