Metadata-Version: 1.1
Name: appdotnet
Version: 0.1.3
Summary: A library for interacting with the App.net API.
Home-page: https://github.com/briancline/appdotnet
Author: Brian Cline
Author-email: bc@brian.fm
License: The BSD License
Platform: UNKNOWN
Classifier: Environment :: Web Environment
Classifier: Intended Audience :: Developers
Classifier: License :: OSI Approved :: BSD License
Classifier: Operating System :: OS Independent
Classifier: Topic :: Software Development :: Libraries :: Python Modules
Classifier: Programming Language :: Python
Classifier: Programming Language :: Python :: 2.7
Classifier: Programming Language :: Python :: 2
